better_feediverse.py
better_feediverse-2.1.0.dist-info/LICENSE
better_feediverse-2.1.0.dist-info/METADATA
better_feediverse-2.1.0.dist-info/WHEEL
better_feediverse-2.1.0.dist-info/entry_points.txt
better_feediverse-2.1.0.dist-info/top_level.txt
better_feediverse-2.1.0.dist-info/RECORD
