Metadata-Version: 2.1
Name: better-feediverse
Version: 2.1.0
Summary: Connect an RSS Feed to Mastodon
Home-page: https://github.com/xopez/better_feediverse
Author: Ed Summers, Xopez
Author-email: 28950736+xopez@users.noreply.github.com
Requires-Python: >=3.3
License-File: LICENSE
Requires-Dist: beautifulsoup4
Requires-Dist: feedparser
Requires-Dist: mastodon.py
Requires-Dist: python-dateutil
Requires-Dist: pyyaml
